{
  "moduleId": "module_12",
  "title": "Inner Conflict & Reflection",
  "language": "en-pl",
  "words": [
    { "en": "left to my own devices", "pl": "pozostawiony samemu sobie" },
    { "en": "come with a", "pl": "przychodzi z" },
    { "en": "vice", "pl": "wada / nałóg" },
    { "en": "end up", "pl": "skończyć (jako / w)" },
    { "en": "in crisis", "pl": "w kryzysie" },
    { "en": "tale", "pl": "opowieść" },
    { "en": "as old as time", "pl": "stara jak świat" },
    { "en": "wake up", "pl": "obudzić się" },
    { "en": "scream", "pl": "krzyczeć" },
    { "en": "one day", "pl": "pewnego dnia" },
    { "en": "watch as you're leaving", "pl": "patrzeć, jak odchodzisz" },
    { "en": "get tired", "pl": "zmęczyć się" },
    { "en": "scheming", "pl": "knucie / spiskowanie" },
    { "en": "for the last time", "pl": "po raz ostatni" },
    { "en": "at tea time", "pl": "w porze herbaty" },
    { "en": "agree", "pl": "zgodzić się" },
    { "en": "stare", "pl": "wpatrywać się" },
    { "en": "directly", "pl": "bezpośrednio" },
    { "en": "mirror", "pl": "lustro" },
    { "en": "exhausting", "pl": "wyczerpujące" },
    { "en": "always", "pl": "zawsze" },
    { "en": "root for", "pl": "kibicować / wspierać" },
    { "en": "anti-hero", "pl": "antybohater" }
  ]
}
